pyomovi/__init__.py
pyomovi/_frontend.py
pyomovi/_version.py
pyomovi/atom_types.py
pyomovi/exceptions.py
pyomovi/visualizer.py
pyomovi/labextension/package.json
pyomovi/labextension/static/480.b1fce5c314dbae3cd0a8.js
pyomovi/labextension/static/568.4ccc6a110b160634c28b.js
pyomovi/labextension/static/569.ae3be51953d4b631954d.js
pyomovi/labextension/static/remoteEntry.309346d848ef43ae0785.js
pyomovi/labextension/static/style.js
pyomovi/labextension/static/third-party-licenses.json
pyomovi/nbextension/extension.js
pyomovi/nbextension/index.js
pyomovi/nbextension/index.js.map
pyomovi/tests/__init__.py
pyomovi/tests/conftest.py
pyomovi/tests/test_example.py
pyomovi/tests/test_nbextension_path.py
pyomovi-0.18.0.data/data/share/jupyter/labextensions/pyomovi/package.json
pyomovi-0.18.0.data/data/share/jupyter/labextensions/pyomovi/static/480.b1fce5c314dbae3cd0a8.js
pyomovi-0.18.0.data/data/share/jupyter/labextensions/pyomovi/static/568.4ccc6a110b160634c28b.js
pyomovi-0.18.0.data/data/share/jupyter/labextensions/pyomovi/static/569.ae3be51953d4b631954d.js
pyomovi-0.18.0.data/data/share/jupyter/labextensions/pyomovi/static/remoteEntry.309346d848ef43ae0785.js
pyomovi-0.18.0.data/data/share/jupyter/labextensions/pyomovi/static/style.js
pyomovi-0.18.0.data/data/share/jupyter/labextensions/pyomovi/static/third-party-licenses.json
pyomovi-0.18.0.data/data/share/jupyter/nbextensions/pyomovi/extension.js
pyomovi-0.18.0.data/data/share/jupyter/nbextensions/pyomovi/index.js
pyomovi-0.18.0.data/data/share/jupyter/nbextensions/pyomovi/index.js.map
pyomovi-0.18.0.data/data/etc/jupyter/nbconfig/notebook.d/pyomovi.json
pyomovi-0.18.0.data/data/share/jupyter/labextensions/pyomovi/install.json
pyomovi-0.18.0.dist-info/METADATA
pyomovi-0.18.0.dist-info/WHEEL
pyomovi-0.18.0.dist-info/licenses/LICENSE.txt
pyomovi-0.18.0.dist-info/RECORD
